dataclass_parser/__init__.py
dataclass_parser/async_parser/__init__.py
dataclass_parser/async_parser/core/__init__.py
dataclass_parser/async_parser/core/base_entity.py
dataclass_parser/async_parser/core/base_mapper.py
dataclass_parser/async_parser/core/fields/__init__.py
dataclass_parser/async_parser/core/fields/base.py
dataclass_parser/async_parser/core/fields/collections.py
dataclass_parser/async_parser/core/fields/complex.py
dataclass_parser/async_parser/core/fields/entity.py
dataclass_parser/async_parser/core/fields/simple.py
dataclass_parser/async_parser/schema/__init__.py
dataclass_parser/async_parser/schema/generator.py
dataclass_parser/core/__init__.py
dataclass_parser/core/base_entity.py
dataclass_parser/core/base_mapper.py
dataclass_parser/core/errors.py
dataclass_parser/core/fields/__init__.py
dataclass_parser/core/fields/base.py
dataclass_parser/core/fields/collections.py
dataclass_parser/core/fields/complex.py
dataclass_parser/core/fields/entity.py
dataclass_parser/core/fields/simple.py
dataclass_parser/examples/__init__.py
dataclass_parser/examples/entities.py
dataclass_parser/examples/orm.py
dataclass_parser/schema/__init__.py
dataclass_parser/schema/generator.py
dataclass_parser-0.1.3.dist-info/LICENSE
dataclass_parser-0.1.3.dist-info/METADATA
dataclass_parser-0.1.3.dist-info/WHEEL
dataclass_parser-0.1.3.dist-info/RECORD
