Metadata-Version: 2.3
Name: dataclass_parser
Version: 0.1.3
Summary: Библиотека для удобного преобразования данных между Python dataclasses и другими форматами
License: MIT
Keywords: dataclass,parser,serialization,deserialization,json
Author: EnterNick
Author-email: python.enter.nick@gmail.com
Requires-Python: >=3.10
Classifier: Programming Language :: Python :: 3
Classifier: Programming Language :: Python :: 3.10
Classifier: Programming Language :: Python :: 3.11
Classifier: Programming Language :: Python :: 3.12
Classifier: License :: OSI Approved :: MIT License
Classifier: Operating System :: OS Independent
Classifier: Development Status :: 4 - Beta
Classifier: Intended Audience :: Developers
Classifier: Topic :: Software Development :: Libraries :: Python Modules
Project-URL: Bug Tracker, https://gitlab.com/sites6821018/dataclass_parser/-/issues
Project-URL: Homepage, https://gitlab.com/sites6821018/dataclass_parser
